small_rag-0.1.3.dist-info/licenses/LICENSE
smallrag/__init__.py
smallrag/__main__.py
smallrag/chunker.py
smallrag/core.py
smallrag/embedder.py
smallrag/preprocessor.py
smallrag/store.py
smallrag/utils.py
small_rag-0.1.3.dist-info/METADATA
small_rag-0.1.3.dist-info/WHEEL
small_rag-0.1.3.dist-info/entry_points.txt
small_rag-0.1.3.dist-info/top_level.txt
small_rag-0.1.3.dist-info/RECORD
