Metadata-Version: 2.4
Name: small-rag
Version: 0.1.3
Summary: A minimal, dependency-free Retrieval-Augmented Generation (RAG) engine using SQLite as a local vector store.
Author-email: "K.S.N.Ganesh" <koradaganesh71@gmail.com>
License: MIT
Project-URL: Homepage, https://github.com/ksnganesh/smallrag
Classifier: Programming Language :: Python :: 3
Classifier: License :: OSI Approved :: MIT License
Classifier: Operating System :: OS Independent
Requires-Python: >=3.9
License-File: LICENSE
Dynamic: license-file
